poprogress/__init__.py
poprogress/api/__init__.py
poprogress/api/tqdm.py
tests/__init__.py
tests/test_progress.py
poprogress-0.0.2.dist-info/LICENSE
poprogress-0.0.2.dist-info/METADATA
poprogress-0.0.2.dist-info/WHEEL
poprogress-0.0.2.dist-info/top_level.txt
poprogress-0.0.2.dist-info/RECORD
